MANIFEST.in
README.rst
requirements.txt
setup.py
test-requirements.txt
redis_utils/__init__.py
redis_utils/bootstrap.py
redis_utils/clear.py
redis_utils/dump.py
redis_utils/load.py
redis_utils/version
redis_utils.egg-info/PKG-INFO
redis_utils.egg-info/SOURCES.txt
redis_utils.egg-info/dependency_links.txt
redis_utils.egg-info/requires.txt
redis_utils.egg-info/top_level.txt