Metadata-Version: 1.1
Name: redis-utils
Version: 1.0.5
Summary: Redis utilities for TDD/BDD
Home-page: http://github.com/jonmorehouse/py-redis-utils
Author: Jon Morehouse
Author-email: morehousej09@gmail.com
License: MIT
Keywords: redis,utilities
Platform: UNKNOWN
Classifier: Development Status :: 4 - Beta
Classifier: Environment :: Console
Classifier: Intended Audience :: Developers
Classifier: License :: OSI Approved :: MIT License
Classifier: Operating System :: OS Independent
Classifier: Programming Language :: Python
Classifier: Programming Language :: Python :: 2.5
Classifier: Programming Language :: Python :: 2.6
Classifier: Programming Language :: Python :: 2.7
Classifier: Programming Language :: Python :: 3
Classifier: Programming Language :: Python :: 3.2
Classifier: Programming Language :: Python :: 3.3
